kdewallet/__init__.py
kdewallet/kdewallet.py
kdewallet-1.0.1.dist-info/METADATA
kdewallet-1.0.1.dist-info/WHEEL
kdewallet-1.0.1.dist-info/top_level.txt
kdewallet-1.0.1.dist-info/RECORD
