Metadata-Version: 2.1
Name: kdewallet
Version: 1.0.1
Summary: kdewallet interface
Home-page: https://github.com/syntaxfiend/kdewallet
Author: Connor Johnson
Author-email: CONjamesNOR@gmail.com
License: GNU
Platform: UNKNOWN
Classifier: Programming Language :: Python :: 3.8
